setup.py
A6/DataEntry.py
A6/Method.py
A6/TextEntry.py
A6/__init__.py
A6/Err/Code.py
A6/Err/Resp.py
A6/Err/__init__.py
A6/ExtraInfo/Info.py
A6/ExtraInfo/Req.py
A6/ExtraInfo/ReqBody.py
A6/ExtraInfo/Resp.py
A6/ExtraInfo/Var.py
A6/ExtraInfo/__init__.py
A6/HTTPReqCall/Action.py
A6/HTTPReqCall/Req.py
A6/HTTPReqCall/Resp.py
A6/HTTPReqCall/Rewrite.py
A6/HTTPReqCall/Stop.py
A6/HTTPReqCall/__init__.py
A6/PrepareConf/Req.py
A6/PrepareConf/Resp.py
A6/PrepareConf/__init__.py
a6pluginprotos.egg-info/PKG-INFO
a6pluginprotos.egg-info/SOURCES.txt
a6pluginprotos.egg-info/dependency_links.txt
a6pluginprotos.egg-info/requires.txt
a6pluginprotos.egg-info/top_level.txt